zipcode/__init__.py
zipcode/department.py
zipcode_sv-1.1.4.dist-info/LICENSE
zipcode_sv-1.1.4.dist-info/WHEEL
zipcode_sv-1.1.4.dist-info/METADATA
zipcode_sv-1.1.4.dist-info/RECORD
