Metadata-Version: 2.1
Name: zipcode-sv
Version: 1.1.4
Summary: A package to get zipcodes from El Salvador departments
Author-email: standoge <stanlydoge@gmail.com>
Classifier: License :: OSI Approved :: GNU General Public License v3 or later (GPLv3+)
Requires-Dist: requests == 2.28.1
Requires-Dist: beautifulsoup4 == 4.11.1
Project-URL: Home, https://github.com/standoge/zipcode-sv
